nagoya_bus_mcp/__init__.py
nagoya_bus_mcp/__main__.py
nagoya_bus_mcp/approach.py
nagoya_bus_mcp/client.py
nagoya_bus_mcp/data.py
nagoya_bus_mcp/py.typed
nagoya_bus_mcp/version.py
nagoya_bus_mcp/mcp/__init__.py
nagoya_bus_mcp/mcp/prompts.py
nagoya_bus_mcp/mcp/server.py
nagoya_bus_mcp/mcp/tools.py
nagoya_bus_mcp-0.7.0.dist-info/licenses/LICENSE
nagoya_bus_mcp-0.7.0.dist-info/METADATA
nagoya_bus_mcp-0.7.0.dist-info/WHEEL
nagoya_bus_mcp-0.7.0.dist-info/entry_points.txt
nagoya_bus_mcp-0.7.0.dist-info/top_level.txt
nagoya_bus_mcp-0.7.0.dist-info/RECORD
