Metadata-Version: 2.4
Name: nagoya-bus-mcp
Version: 0.7.0
Summary: Model Context Protocol (MCP) server providing tools to query Nagoya City bus timetables
Author-email: Yusuke Miyazaki <miyazaki.dev@gmail.com>
Maintainer-email: Yusuke Miyazaki <miyazaki.dev@gmail.com>
License-Expression: MIT
Project-URL: Homepage, https://github.com/ymyzk/nagoya-bus-mcp
Project-URL: Repository, https://github.com/ymyzk/nagoya-bus-mcp
Project-URL: Issues, https://github.com/ymyzk/nagoya-bus-mcp/issues
Keywords: mcp,model context protocol,fastmcp,nagoya,bus,public transport,transit
Classifier: Development Status :: 3 - Alpha
Classifier: Programming Language :: Python :: 3
Classifier: Programming Language :: Python :: 3 :: Only
Classifier: Programming Language :: Python :: 3.11
Classifier: Programming Language :: Python :: 3.12
Classifier: Programming Language :: Python :: 3.13
Classifier: Programming Language :: Python :: 3.14
Classifier: Topic :: Utilities
Classifier: Typing :: Typed
Requires-Python: >=3.11
License-File: LICENSE
Requires-Dist: fastmcp>=2.13.1
Requires-Dist: hishel[httpx]>=1.1.7
Requires-Dist: httpx>=0.28.1
Requires-Dist: pydantic>=2.11.7
Dynamic: license-file
